foauth2.py
setup.cfg
setup.py
foauth2.egg-info/PKG-INFO
foauth2.egg-info/SOURCES.txt
foauth2.egg-info/dependency_links.txt
foauth2.egg-info/top_level.txt
foauth2.egg-info/zip-safe