Metadata-Version: 1.1
Name: foauth2
Version: 0.9
Summary: Library for OAuth version 2 'Bearer Token'
Home-page: http://github.com/jackdied/foauth2
Author: Jack Diederich
Author-email: jackdied@gmail.com
License: MIT License
Keywords: oauth
Platform: UNKNOWN
Classifier: Intended Audience :: Developers
Classifier: Intended Audience :: System Administrators
Classifier: License :: OSI Approved :: Apache Software License
Classifier: Programming Language :: Python
Classifier: Development Status :: 4 - Beta
Classifier: Programming Language :: Python
Classifier: Programming Language :: Python :: 2.7
Classifier: Operating System :: OS Independent
Classifier: Topic :: Software Development :: Libraries
Classifier: Topic :: Software Development :: Libraries :: Python Modules
